template.py
sensus-0.0.1.dist-info/METADATA
sensus-0.0.1.dist-info/WHEEL
sensus-0.0.1.dist-info/top_level.txt
sensus-0.0.1.dist-info/RECORD
