Metadata-Version: 2.1
Name: sensus
Version: 0.0.1
Summary: this is just a template
Home-page: http://packages.python.org/an_example_pypi_project
Author: Farzad
Author-email: farzadziaien@gmail.com
License: BSD
Keywords: example documentation tutorial
Platform: Windows
Platform: Linux
Classifier: Development Status :: 1 - Planning
Classifier: Topic :: Education :: Testing
Classifier: License :: OSI Approved :: MIT License
Requires-Python: >=3.8
Requires-Dist: numpy (>1.0.0)
Provides-Extra: dev
Requires-Dist: pytest (>=3.7) ; extra == 'dev'
